{
  "openapi": "3.0.1",
  "info": {
    "title": "KrishiEye.Services.Catalog.API",
    "version": "1.0"
  },
  "paths": {
    "/api/Categories": {
      "get": {
        "tags": [
          "Categories"
        ],
        "parameters": [
          {
            "name": "productTypeId",
            "in": "query",
            "schema": {
              "type": "string",
              "format": "uuid"
            }
          }
        ],
        "responses": {
          "200": {
            "description": "OK",
            "content": {
              "text/plain": {
                "schema": {
                  "type": "array",
                  "items": {
                    "$ref": "#/components/schemas/CategoryDto"
                  }
                }
              },
              "application/json": {
                "schema": {
                  "type": "array",
                  "items": {
                    "$ref": "#/components/schemas/CategoryDto"
                  }
                }
              },
              "text/json": {
                "schema": {
                  "type": "array",
                  "items": {
                    "$ref": "#/components/schemas/CategoryDto"
                  }
                }
              }
            }
          }
        }
      },
      "post": {
        "tags": [
          "Categories"
        ],
        "requestBody": {
          "content": {
            "application/json": {
              "schema": {
                "$ref": "#/components/schemas/CreateCategoryCommand"
              }
            },
            "text/json": {
              "schema": {
                "$ref": "#/components/schemas/CreateCategoryCommand"
              }
            },
            "application/*+json": {
              "schema": {
                "$ref": "#/components/schemas/CreateCategoryCommand"
              }
            }
          }
        },
        "responses": {
          "200": {
            "description": "OK",
            "content": {
              "text/plain": {
                "schema": {
                  "type": "string",
                  "format": "uuid"
                }
              },
              "application/json": {
                "schema": {
                  "type": "string",
                  "format": "uuid"
                }
              },
              "text/json": {
                "schema": {
                  "type": "string",
                  "format": "uuid"
                }
              }
            }
          }
        }
      }
    },
    "/api/Categories/{id}": {
      "get": {
        "tags": [
          "Categories"
        ],
        "parameters": [
          {
            "name": "id",
            "in": "path",
            "required": true,
            "schema": {
              "type": "string",
              "format": "uuid"
            }
          }
        ],
        "responses": {
          "200": {
            "description": "OK",
            "content": {
              "text/plain": {
                "schema": {
                  "$ref": "#/components/schemas/CategoryDto"
                }
              },
              "application/json": {
                "schema": {
                  "$ref": "#/components/schemas/CategoryDto"
                }
              },
              "text/json": {
                "schema": {
                  "$ref": "#/components/schemas/CategoryDto"
                }
              }
            }
          }
        }
      },
      "put": {
        "tags": [
          "Categories"
        ],
        "parameters": [
          {
            "name": "id",
            "in": "path",
            "required": true,
            "schema": {
              "type": "string",
              "format": "uuid"
            }
          }
        ],
        "requestBody": {
          "content": {
            "application/json": {
              "schema": {
                "$ref": "#/components/schemas/UpdateCategoryRequest"
              }
            },
            "text/json": {
              "schema": {
                "$ref": "#/components/schemas/UpdateCategoryRequest"
              }
            },
            "application/*+json": {
              "schema": {
                "$ref": "#/components/schemas/UpdateCategoryRequest"
              }
            }
          }
        },
        "responses": {
          "200": {
            "description": "OK"
          }
        }
      },
      "delete": {
        "tags": [
          "Categories"
        ],
        "parameters": [
          {
            "name": "id",
            "in": "path",
            "required": true,
            "schema": {
              "type": "string",
              "format": "uuid"
            }
          }
        ],
        "responses": {
          "200": {
            "description": "OK"
          }
        }
      }
    },
    "/api/Products": {
      "get": {
        "tags": [
          "Products"
        ],
        "parameters": [
          {
            "name": "searchTerm",
            "in": "query",
            "schema": {
              "type": "string"
            }
          },
          {
            "name": "categoryId",
            "in": "query",
            "schema": {
              "type": "string",
              "format": "uuid"
            }
          },
          {
            "name": "minPrice",
            "in": "query",
            "schema": {
              "type": "number",
              "format": "double"
            }
          },
          {
            "name": "maxPrice",
            "in": "query",
            "schema": {
              "type": "number",
              "format": "double"
            }
          },
          {
            "name": "inStockOnly",
            "in": "query",
            "schema": {
              "type": "boolean"
            }
          },
          {
            "name": "skip",
            "in": "query",
            "schema": {
              "type": "integer",
              "format": "int32",
              "default": 0
            }
          },
          {
            "name": "take",
            "in": "query",
            "schema": {
              "type": "integer",
              "format": "int32",
              "default": 20
            }
          }
        ],
        "responses": {
          "200": {
            "description": "OK",
            "content": {
              "text/plain": {
                "schema": {
                  "$ref": "#/components/schemas/SearchProductsResult"
                }
              },
              "application/json": {
                "schema": {
                  "$ref": "#/components/schemas/SearchProductsResult"
                }
              },
              "text/json": {
                "schema": {
                  "$ref": "#/components/schemas/SearchProductsResult"
                }
              }
            }
          }
        }
      },
      "post": {
        "tags": [
          "Products"
        ],
        "requestBody": {
          "content": {
            "application/json": {
              "schema": {
                "$ref": "#/components/schemas/CreateProductCommand"
              }
            },
            "text/json": {
              "schema": {
                "$ref": "#/components/schemas/CreateProductCommand"
              }
            },
            "application/*+json": {
              "schema": {
                "$ref": "#/components/schemas/CreateProductCommand"
              }
            }
          }
        },
        "responses": {
          "200": {
            "description": "OK",
            "content": {
              "text/plain": {
                "schema": {
                  "type": "string",
                  "format": "uuid"
                }
              },
              "application/json": {
                "schema": {
                  "type": "string",
                  "format": "uuid"
                }
              },
              "text/json": {
                "schema": {
                  "type": "string",
                  "format": "uuid"
                }
              }
            }
          }
        }
      }
    },
    "/api/Products/{id}": {
      "get": {
        "tags": [
          "Products"
        ],
        "parameters": [
          {
            "name": "id",
            "in": "path",
            "required": true,
            "schema": {
              "type": "string",
              "format": "uuid"
            }
          }
        ],
        "responses": {
          "200": {
            "description": "OK",
            "content": {
              "text/plain": {
                "schema": {
                  "$ref": "#/components/schemas/ProductDto"
                }
              },
              "application/json": {
                "schema": {
                  "$ref": "#/components/schemas/ProductDto"
                }
              },
              "text/json": {
                "schema": {
                  "$ref": "#/components/schemas/ProductDto"
                }
              }
            }
          }
        }
      },
      "put": {
        "tags": [
          "Products"
        ],
        "parameters": [
          {
            "name": "id",
            "in": "path",
            "required": true,
            "schema": {
              "type": "string",
              "format": "uuid"
            }
          }
        ],
        "requestBody": {
          "content": {
            "application/json": {
              "schema": {
                "$ref": "#/components/schemas/UpdateProductRequest"
              }
            },
            "text/json": {
              "schema": {
                "$ref": "#/components/schemas/UpdateProductRequest"
              }
            },
            "application/*+json": {
              "schema": {
                "$ref": "#/components/schemas/UpdateProductRequest"
              }
            }
          }
        },
        "responses": {
          "200": {
            "description": "OK"
          }
        }
      },
      "delete": {
        "tags": [
          "Products"
        ],
        "parameters": [
          {
            "name": "id",
            "in": "path",
            "required": true,
            "schema": {
              "type": "string",
              "format": "uuid"
            }
          }
        ],
        "responses": {
          "200": {
            "description": "OK"
          }
        }
      }
    },
    "/api/Products/slug/{slug}": {
      "get": {
        "tags": [
          "Products"
        ],
        "parameters": [
          {
            "name": "slug",
            "in": "path",
            "required": true,
            "schema": {
              "type": "string"
            }
          }
        ],
        "responses": {
          "200": {
            "description": "OK",
            "content": {
              "text/plain": {
                "schema": {
                  "$ref": "#/components/schemas/ProductDto"
                }
              },
              "application/json": {
                "schema": {
                  "$ref": "#/components/schemas/ProductDto"
                }
              },
              "text/json": {
                "schema": {
                  "$ref": "#/components/schemas/ProductDto"
                }
              }
            }
          }
        }
      }
    },
    "/api/Products/seller/{sellerId}": {
      "get": {
        "tags": [
          "Products"
        ],
        "parameters": [
          {
            "name": "sellerId",
            "in": "path",
            "required": true,
            "schema": {
              "type": "string",
              "format": "uuid"
            }
          }
        ],
        "responses": {
          "200": {
            "description": "OK",
            "content": {
              "text/plain": {
                "schema": {
                  "type": "array",
                  "items": {
                    "$ref": "#/components/schemas/ProductDto"
                  }
                }
              },
              "application/json": {
                "schema": {
                  "type": "array",
                  "items": {
                    "$ref": "#/components/schemas/ProductDto"
                  }
                }
              },
              "text/json": {
                "schema": {
                  "type": "array",
                  "items": {
                    "$ref": "#/components/schemas/ProductDto"
                  }
                }
              }
            }
          }
        }
      }
    },
    "/api/ProductTypes": {
      "get": {
        "tags": [
          "ProductTypes"
        ],
        "responses": {
          "200": {
            "description": "OK",
            "content": {
              "text/plain": {
                "schema": {
                  "type": "array",
                  "items": {
                    "$ref": "#/components/schemas/ProductTypeDto"
                  }
                }
              },
              "application/json": {
                "schema": {
                  "type": "array",
                  "items": {
                    "$ref": "#/components/schemas/ProductTypeDto"
                  }
                }
              },
              "text/json": {
                "schema": {
                  "type": "array",
                  "items": {
                    "$ref": "#/components/schemas/ProductTypeDto"
                  }
                }
              }
            }
          }
        }
      },
      "post": {
        "tags": [
          "ProductTypes"
        ],
        "requestBody": {
          "content": {
            "application/json": {
              "schema": {
                "$ref": "#/components/schemas/CreateProductTypeCommand"
              }
            },
            "text/json": {
              "schema": {
                "$ref": "#/components/schemas/CreateProductTypeCommand"
              }
            },
            "application/*+json": {
              "schema": {
                "$ref": "#/components/schemas/CreateProductTypeCommand"
              }
            }
          }
        },
        "responses": {
          "200": {
            "description": "OK",
            "content": {
              "text/plain": {
                "schema": {
                  "type": "string",
                  "format": "uuid"
                }
              },
              "application/json": {
                "schema": {
                  "type": "string",
                  "format": "uuid"
                }
              },
              "text/json": {
                "schema": {
                  "type": "string",
                  "format": "uuid"
                }
              }
            }
          }
        }
      }
    },
    "/api/ProductTypes/{id}": {
      "get": {
        "tags": [
          "ProductTypes"
        ],
        "parameters": [
          {
            "name": "id",
            "in": "path",
            "required": true,
            "schema": {
              "type": "string",
              "format": "uuid"
            }
          }
        ],
        "responses": {
          "200": {
            "description": "OK",
            "content": {
              "text/plain": {
                "schema": {
                  "$ref": "#/components/schemas/ProductTypeDto"
                }
              },
              "application/json": {
                "schema": {
                  "$ref": "#/components/schemas/ProductTypeDto"
                }
              },
              "text/json": {
                "schema": {
                  "$ref": "#/components/schemas/ProductTypeDto"
                }
              }
            }
          }
        }
      },
      "put": {
        "tags": [
          "ProductTypes"
        ],
        "parameters": [
          {
            "name": "id",
            "in": "path",
            "required": true,
            "schema": {
              "type": "string",
              "format": "uuid"
            }
          }
        ],
        "requestBody": {
          "content": {
            "application/json": {
              "schema": {
                "$ref": "#/components/schemas/UpdateProductTypeRequest"
              }
            },
            "text/json": {
              "schema": {
                "$ref": "#/components/schemas/UpdateProductTypeRequest"
              }
            },
            "application/*+json": {
              "schema": {
                "$ref": "#/components/schemas/UpdateProductTypeRequest"
              }
            }
          }
        },
        "responses": {
          "200": {
            "description": "OK"
          }
        }
      },
      "delete": {
        "tags": [
          "ProductTypes"
        ],
        "parameters": [
          {
            "name": "id",
            "in": "path",
            "required": true,
            "schema": {
              "type": "string",
              "format": "uuid"
            }
          }
        ],
        "responses": {
          "200": {
            "description": "OK"
          }
        }
      }
    },
    "/api/Units": {
      "get": {
        "tags": [
          "Units"
        ],
        "responses": {
          "200": {
            "description": "OK",
            "content": {
              "text/plain": {
                "schema": {
                  "type": "array",
                  "items": {
                    "$ref": "#/components/schemas/UnitDto"
                  }
                }
              },
              "application/json": {
                "schema": {
                  "type": "array",
                  "items": {
                    "$ref": "#/components/schemas/UnitDto"
                  }
                }
              },
              "text/json": {
                "schema": {
                  "type": "array",
                  "items": {
                    "$ref": "#/components/schemas/UnitDto"
                  }
                }
              }
            }
          }
        }
      },
      "post": {
        "tags": [
          "Units"
        ],
        "requestBody": {
          "content": {
            "application/json": {
              "schema": {
                "$ref": "#/components/schemas/CreateUnitCommand"
              }
            },
            "text/json": {
              "schema": {
                "$ref": "#/components/schemas/CreateUnitCommand"
              }
            },
            "application/*+json": {
              "schema": {
                "$ref": "#/components/schemas/CreateUnitCommand"
              }
            }
          }
        },
        "responses": {
          "200": {
            "description": "OK",
            "content": {
              "text/plain": {
                "schema": {
                  "type": "string",
                  "format": "uuid"
                }
              },
              "application/json": {
                "schema": {
                  "type": "string",
                  "format": "uuid"
                }
              },
              "text/json": {
                "schema": {
                  "type": "string",
                  "format": "uuid"
                }
              }
            }
          }
        }
      }
    },
    "/api/Units/{id}": {
      "get": {
        "tags": [
          "Units"
        ],
        "parameters": [
          {
            "name": "id",
            "in": "path",
            "required": true,
            "schema": {
              "type": "string",
              "format": "uuid"
            }
          }
        ],
        "responses": {
          "200": {
            "description": "OK",
            "content": {
              "text/plain": {
                "schema": {
                  "$ref": "#/components/schemas/UnitDto"
                }
              },
              "application/json": {
                "schema": {
                  "$ref": "#/components/schemas/UnitDto"
                }
              },
              "text/json": {
                "schema": {
                  "$ref": "#/components/schemas/UnitDto"
                }
              }
            }
          }
        }
      },
      "put": {
        "tags": [
          "Units"
        ],
        "parameters": [
          {
            "name": "id",
            "in": "path",
            "required": true,
            "schema": {
              "type": "string",
              "format": "uuid"
            }
          }
        ],
        "requestBody": {
          "content": {
            "application/json": {
              "schema": {
                "$ref": "#/components/schemas/UpdateUnitRequest"
              }
            },
            "text/json": {
              "schema": {
                "$ref": "#/components/schemas/UpdateUnitRequest"
              }
            },
            "application/*+json": {
              "schema": {
                "$ref": "#/components/schemas/UpdateUnitRequest"
              }
            }
          }
        },
        "responses": {
          "200": {
            "description": "OK"
          }
        }
      },
      "delete": {
        "tags": [
          "Units"
        ],
        "parameters": [
          {
            "name": "id",
            "in": "path",
            "required": true,
            "schema": {
              "type": "string",
              "format": "uuid"
            }
          }
        ],
        "responses": {
          "200": {
            "description": "OK"
          }
        }
      }
    }
  },
  "components": {
    "schemas": {
      "CategoryDto": {
        "type": "object",
        "properties": {
          "id": {
            "type": "string",
            "format": "uuid"
          },
          "name": {
            "type": "string",
            "nullable": true
          },
          "description": {
            "type": "string",
            "nullable": true
          },
          "productTypeId": {
            "type": "string",
            "format": "uuid"
          },
          "productTypeName": {
            "type": "string",
            "nullable": true
          },
          "parentCategoryId": {
            "type": "string",
            "format": "uuid",
            "nullable": true
          },
          "parentCategoryName": {
            "type": "string",
            "nullable": true
          },
          "urlSlug": {
            "type": "string",
            "nullable": true
          },
          "metaTitle": {
            "type": "string",
            "nullable": true
          },
          "metaDescription": {
            "type": "string",
            "nullable": true
          },
          "createdAt": {
            "type": "string",
            "format": "date-time"
          }
        },
        "additionalProperties": false
      },
      "CreateCategoryCommand": {
        "type": "object",
        "properties": {
          "name": {
            "type": "string",
            "nullable": true
          },
          "description": {
            "type": "string",
            "nullable": true
          },
          "productTypeId": {
            "type": "string",
            "format": "uuid"
          },
          "urlSlug": {
            "type": "string",
            "nullable": true
          },
          "metaTitle": {
            "type": "string",
            "nullable": true
          },
          "metaDescription": {
            "type": "string",
            "nullable": true
          },
          "parentCategoryId": {
            "type": "string",
            "format": "uuid",
            "nullable": true
          }
        },
        "additionalProperties": false
      },
      "CreateProductCommand": {
        "type": "object",
        "properties": {
          "name": {
            "type": "string",
            "nullable": true
          },
          "description": {
            "type": "string",
            "nullable": true
          },
          "priceAmount": {
            "type": "number",
            "format": "double"
          },
          "currency": {
            "type": "string",
            "nullable": true
          },
          "stockQuantity": {
            "type": "integer",
            "format": "int32"
          },
          "unitId": {
            "type": "string",
            "format": "uuid"
          },
          "imageUrl": {
            "type": "string",
            "nullable": true
          },
          "sellerId": {
            "type": "string",
            "format": "uuid"
          },
          "productTypeId": {
            "type": "string",
            "format": "uuid"
          },
          "categoryId": {
            "type": "string",
            "format": "uuid"
          },
          "urlSlug": {
            "type": "string",
            "nullable": true
          },
          "metaTitle": {
            "type": "string",
            "nullable": true
          },
          "metaDescription": {
            "type": "string",
            "nullable": true
          },
          "metaKeywords": {
            "type": "string",
            "nullable": true
          },
          "ogTitle": {
            "type": "string",
            "nullable": true
          },
          "ogDescription": {
            "type": "string",
            "nullable": true
          },
          "ogImage": {
            "type": "string",
            "nullable": true
          }
        },
        "additionalProperties": false
      },
      "CreateProductTypeCommand": {
        "type": "object",
        "properties": {
          "name": {
            "type": "string",
            "nullable": true
          },
          "description": {
            "type": "string",
            "nullable": true
          },
          "urlSlug": {
            "type": "string",
            "nullable": true
          },
          "metaTitle": {
            "type": "string",
            "nullable": true
          },
          "metaDescription": {
            "type": "string",
            "nullable": true
          }
        },
        "additionalProperties": false
      },
      "CreateUnitCommand": {
        "type": "object",
        "properties": {
          "name": {
            "type": "string",
            "nullable": true
          },
          "symbol": {
            "type": "string",
            "nullable": true
          },
          "unitType": {
            "$ref": "#/components/schemas/UnitType"
          }
        },
        "additionalProperties": false
      },
      "ProductDto": {
        "type": "object",
        "properties": {
          "id": {
            "type": "string",
            "format": "uuid"
          },
          "name": {
            "type": "string",
            "nullable": true
          },
          "description": {
            "type": "string",
            "nullable": true
          },
          "price": {
            "type": "number",
            "format": "double"
          },
          "currency": {
            "type": "string",
            "nullable": true
          },
          "stockQuantity": {
            "type": "integer",
            "format": "int32"
          },
          "imageUrl": {
            "type": "string",
            "nullable": true
          },
          "isInStock": {
            "type": "boolean"
          },
          "productTypeName": {
            "type": "string",
            "nullable": true
          },
          "categoryName": {
            "type": "string",
            "nullable": true
          },
          "unitName": {
            "type": "string",
            "nullable": true
          },
          "unitSymbol": {
            "type": "string",
            "nullable": true
          },
          "urlSlug": {
            "type": "string",
            "nullable": true
          },
          "metaTitle": {
            "type": "string",
            "nullable": true
          },
          "metaDescription": {
            "type": "string",
            "nullable": true
          },
          "createdAt": {
            "type": "string",
            "format": "date-time"
          }
        },
        "additionalProperties": false
      },
      "ProductTypeDto": {
        "type": "object",
        "properties": {
          "id": {
            "type": "string",
            "format": "uuid"
          },
          "name": {
            "type": "string",
            "nullable": true
          },
          "description": {
            "type": "string",
            "nullable": true
          },
          "urlSlug": {
            "type": "string",
            "nullable": true
          },
          "metaTitle": {
            "type": "string",
            "nullable": true
          },
          "metaDescription": {
            "type": "string",
            "nullable": true
          },
          "createdAt": {
            "type": "string",
            "format": "date-time"
          }
        },
        "additionalProperties": false
      },
      "SearchProductsResult": {
        "type": "object",
        "properties": {
          "products": {
            "type": "array",
            "items": {
              "$ref": "#/components/schemas/ProductDto"
            },
            "nullable": true
          },
          "totalCount": {
            "type": "integer",
            "format": "int32"
          },
          "skip": {
            "type": "integer",
            "format": "int32"
          },
          "take": {
            "type": "integer",
            "format": "int32"
          }
        },
        "additionalProperties": false
      },
      "UnitDto": {
        "type": "object",
        "properties": {
          "id": {
            "type": "string",
            "format": "uuid"
          },
          "name": {
            "type": "string",
            "nullable": true
          },
          "symbol": {
            "type": "string",
            "nullable": true
          },
          "unitType": {
            "$ref": "#/components/schemas/UnitType"
          },
          "createdAt": {
            "type": "string",
            "format": "date-time"
          }
        },
        "additionalProperties": false
      },
      "UnitType": {
        "enum": [
          1,
          2,
          3,
          4,
          5,
          6
        ],
        "type": "integer",
        "format": "int32"
      },
      "UpdateCategoryRequest": {
        "type": "object",
        "properties": {
          "name": {
            "type": "string",
            "nullable": true
          },
          "description": {
            "type": "string",
            "nullable": true
          },
          "urlSlug": {
            "type": "string",
            "nullable": true
          },
          "metaTitle": {
            "type": "string",
            "nullable": true
          },
          "metaDescription": {
            "type": "string",
            "nullable": true
          }
        },
        "additionalProperties": false
      },
      "UpdateProductRequest": {
        "type": "object",
        "properties": {
          "name": {
            "type": "string",
            "nullable": true
          },
          "description": {
            "type": "string",
            "nullable": true
          },
          "price": {
            "type": "number",
            "format": "double"
          },
          "currency": {
            "type": "string",
            "nullable": true
          },
          "stockQuantity": {
            "type": "integer",
            "format": "int32"
          },
          "imageUrl": {
            "type": "string",
            "nullable": true
          }
        },
        "additionalProperties": false
      },
      "UpdateProductTypeRequest": {
        "type": "object",
        "properties": {
          "name": {
            "type": "string",
            "nullable": true
          },
          "description": {
            "type": "string",
            "nullable": true
          },
          "urlSlug": {
            "type": "string",
            "nullable": true
          },
          "metaTitle": {
            "type": "string",
            "nullable": true
          },
          "metaDescription": {
            "type": "string",
            "nullable": true
          }
        },
        "additionalProperties": false
      },
      "UpdateUnitRequest": {
        "type": "object",
        "properties": {
          "name": {
            "type": "string",
            "nullable": true
          },
          "symbol": {
            "type": "string",
            "nullable": true
          },
          "unitType": {
            "type": "integer",
            "format": "int32"
          }
        },
        "additionalProperties": false
      }
    }
  }
}